OBP_logging_v4/__init__.py
OBP_logging_v4/cloudwatch.py
OBP_logging_v4/rds.py
OBP_logging_v4/utils.py
OBP_logging_v4-0.0.2.dist-info/METADATA
OBP_logging_v4-0.0.2.dist-info/WHEEL
OBP_logging_v4-0.0.2.dist-info/top_level.txt
OBP_logging_v4-0.0.2.dist-info/RECORD
